pystospa-2.0.19.dist-info/RECORD
pystospa-2.0.19.dist-info/WHEEL
pystospa-2.0.19.dist-info/METADATA
pystospa-2.0.19.dist-info/top_level.txt
pystospa-2.0.19.dist-info/LICENCE
pystospa/__init__.py
pystospa/pystospa.cpython-35m-x86_64-linux-gnu.so
