Metadata-Version: 2.1
Name: pystospa
Version: 2.0.19
Summary: A python binding of C++ package for stochastic simulations of spatially extended systems
Home-page: UNKNOWN
Author: Bartosz Bartmanski
Author-email: bartoszbartmanski@gmail.com
License: UNKNOWN
Platform: Linux
